[
    {
        "rank": 1,
        "brand": "어노브",
        "name": "어노브 딥 데미지 헤어 트리트먼트 EX 320ml 벚꽃/더블/듀오 기획",
        "price": "28,900",
        "updated_at": "2026-03-06 15:31:24"
    },
    {
        "rank": 2,
        "brand": "웰라쥬",
        "name": "[스테디셀러특가][속건조앰플] 웰라쥬 리얼 히알루로닉 블루 100 앰플 75ml 더블 기획 (+마스크1매)",
        "price": "29,300",
        "updated_at": "2026-03-06 15:31:24"
    },
    {
        "rank": 3,
        "brand": "메디힐",
        "name": "[3월 올영픽/15년연속 1위] 메디힐 에센셜 마스크팩 10+1/10매 기획 7종 골라담기",
        "price": "9,900",
        "updated_at": "2026-03-06 15:31:24"
    },
    {
        "rank": 4,
        "brand": "어노브",
        "name": "[3월 올영세일 한정기획] 어노브 딥 데미지 리페어 샴푸 500g 벚꽃/더블/듀오 기획",
        "price": "25,500",
        "updated_at": "2026-03-06 15:31:24"
    },
    {
        "rank": 5,
        "brand": "파티온",
        "name": "[트러블1등/단독기획] 파티온 노스카나인 트러블 세럼 50ml 기획(+15ml+마스크 1매)",
        "price": "26,300",
        "updated_at": "2026-03-06 15:31:24"
    },
    {
        "rank": 6,
        "brand": "어노브",
        "name": "어노브 실크 헤어 오일 에센스 70ml 벚꽃/더블 기획",
        "price": "27,500",
        "updated_at": "2026-03-06 15:31:24"
    },
    {
        "rank": 7,
        "brand": "에스트라",
        "name": "[올영세일] 에스트라 아토베리어365 크림 80ml 어워즈 한정기획 (+30ml+앰플 3ml)",
        "price": "24,700",
        "updated_at": "2026-03-06 15:31:24"
    },
    {
        "rank": 8,
        "brand": "아누아",
        "name": "[스테디셀러특가] 아누아 피디알엔 히알루론산 캡슐 100 세럼 30ml 더블 기획",
        "price": "28,500",
        "updated_at": "2026-03-06 15:31:24"
    },
    {
        "rank": 9,
        "brand": "메디힐",
        "name": "[3월 올영픽/단독기획] 메디힐 더마 패드 200매 대용량 기획 세트 7종 골라담기",
        "price": "27,400",
        "updated_at": "2026-03-06 15:31:24"
    },
    {
        "rank": 10,
        "brand": "넘버즈인",
        "name": "[10매] 넘버즈인 1번~5번 마스크팩 10매 기획 5종 중 택 1",
        "price": "17,370",
        "updated_at": "2026-03-06 15:31:24"
    },
    {
        "rank": 11,
        "brand": "넘버즈인",
        "name": "[1번패드추가증정/대용량140매] 넘버즈인 토너패드 리필 기획 (1번, 4번, 5번)",
        "price": "25,560",
        "updated_at": "2026-03-06 15:31:24"
    },
    {
        "rank": 12,
        "brand": "달바",
        "name": "[스테디셀러특가][NO.1 미스트세럼] 달바 퍼스트 스프레이 세럼 100ml 2개 기획",
        "price": "30,900",
        "updated_at": "2026-03-06 15:31:24"
    },
    {
        "rank": 13,
        "brand": "밀잇",
        "name": "[스테디셀러특가][1+1] 밀잇 식단관리 단백질쉐이크 40g 7종 택1",
        "price": "3,510",
        "updated_at": "2026-03-06 15:31:24"
    },
    {
        "rank": 14,
        "brand": "닥터지",
        "name": "[3월올영픽/구매인증/쫀냐미] 닥터지 레드 블레미쉬 클리어 수딩크림 70+30ml+세럼20ml 기획 (+인형키링 증정)",
        "price": "25,900",
        "updated_at": "2026-03-06 15:31:24"
    },
    {
        "rank": 15,
        "brand": "메디필",
        "name": "[한정특가/모공쏙폼] 메디필 레드 락토 콜라겐 클리어 폼 2.0 대용량 300ml 기획 (+해면)",
        "price": "11,880",
        "updated_at": "2026-03-06 15:31:24"
    },
    {
        "rank": 16,
        "brand": "메디힐",
        "name": "[단독기획] 메디힐 콜라겐 캡슐 패치 60+60매 더블 기획 2종 (레티놀, 비타민C)",
        "price": "24,820",
        "updated_at": "2026-03-06 15:31:24"
    },
    {
        "rank": 17,
        "brand": "토리든",
        "name": "[3월올영픽/1위세럼]토리든 다이브인 저분자 히알루론산 세럼 50ml 한정 리필 기획",
        "price": "25,920",
        "updated_at": "2026-03-06 15:31:24"
    },
    {
        "rank": 18,
        "brand": "파티온",
        "name": "[단독기획/대용량] 파티온 노스카나인 트러블 크림 75ml 기획(+5ml)",
        "price": "28,800",
        "updated_at": "2026-03-06 15:31:24"
    },
    {
        "rank": 19,
        "brand": "메디큐브",
        "name": "[3월단독/1등모공패드]메디큐브 제로 모공 패드 150매 한정기획 (패드 3종 택1)",
        "price": "27,460",
        "updated_at": "2026-03-06 15:31:24"
    },
    {
        "rank": 20,
        "brand": "바이오힐보",
        "name": "[탄력보습크림| 어워즈 수상] 바이오힐보 프로바이오덤 3D 리프팅 크림 50ml [단품/리필 기획]",
        "price": "38,900",
        "updated_at": "2026-03-06 15:31:24"
    }
]