[
    {
        "rank": 1,
        "brand": "연작",
        "name": "[4월올영픽/10ml 증정기획] 연작 스킨 퍼펙팅 프로텍티브 베이스 프렙 25ml/40ml",
        "price": "27,900",
        "updated_at": "2026-04-24 16:00:40"
    },
    {
        "rank": 2,
        "brand": "세포랩",
        "name": "[리뷰이벤트] 세포랩 바이오제닉 에센스 블렌디드 포뮬라 50% 100ml",
        "price": "32,900",
        "updated_at": "2026-04-24 16:00:40"
    },
    {
        "rank": 3,
        "brand": "쏘내추럴",
        "name": "[4월 올영픽 한정기획] 쏘내추럴 올 데이 타이트 메이크업 세팅 픽서 120ml 더블기획 (120ml+120ml)",
        "price": "31,900",
        "updated_at": "2026-04-24 16:00:40"
    },
    {
        "rank": 4,
        "brand": "메디힐",
        "name": "[15년 연속 1위] 메디힐 에센셜 마스크팩 10매/10+1매 기획 7종 골라담기",
        "price": "10,000",
        "updated_at": "2026-04-24 16:00:41"
    },
    {
        "rank": 5,
        "brand": "라운드랩",
        "name": "[4월 한정/선스틱 증정] 라운드랩 자작나무 수분 톤업 선크림 50ml 1+1 기획 (+소나무 선스틱 10g)",
        "price": "24,500",
        "updated_at": "2026-04-24 16:00:41"
    },
    {
        "rank": 6,
        "brand": "메디힐",
        "name": "[1위 패드] 메디힐 더마 패드 200매 대용량 기획 세트 7종 골라담기",
        "price": "28,900",
        "updated_at": "2026-04-24 16:00:41"
    },
    {
        "rank": 7,
        "brand": "에스트라",
        "name": "[4월 올영픽][2025어워즈1위] 에스트라 아토베리어365 크림 80ml 기획 (+하이드로 에센스25ml+앰플7ml)",
        "price": "25,000",
        "updated_at": "2026-04-24 16:00:41"
    },
    {
        "rank": 8,
        "brand": "메디큐브",
        "name": "[100% 리뷰이벤트/1등모공패드] 메디큐브 제로 모공 패드 150매 한정기획 (패드 3종 택1)",
        "price": "27,900",
        "updated_at": "2026-04-24 16:00:41"
    },
    {
        "rank": 9,
        "brand": "에스네이처",
        "name": "[1+1+역대급증정/4월올영픽/모공수분천재크림] 에스네이처 아쿠아 스쿠알란 수분크림 60ml 더블기획 (+파우치키링)",
        "price": "22,300",
        "updated_at": "2026-04-24 16:00:41"
    },
    {
        "rank": 10,
        "brand": "토리든",
        "name": "[더블기획/1+1] 토리든 다이브인 히알루론산 수딩 크림 더블기획 (100ml+100ml)",
        "price": "29,930",
        "updated_at": "2026-04-24 16:00:41"
    },
    {
        "rank": 11,
        "brand": "딜라이트 프로젝트",
        "name": "딜라이트 프로젝트 프레첼 3종 택1",
        "price": "2,160",
        "updated_at": "2026-04-24 16:00:41"
    },
    {
        "rank": 12,
        "brand": "비플레인",
        "name": "[4월올영픽/말끔모공] 비플레인 녹두 약산성 클렌징폼 160ml 더블 기획",
        "price": "23,400",
        "updated_at": "2026-04-24 16:00:41"
    },
    {
        "rank": 13,
        "brand": "플라이밀",
        "name": "플라이밀 쉐이크 630g 보틀기획 (14종 택 1)",
        "price": "27,900",
        "updated_at": "2026-04-24 16:00:41"
    },
    {
        "rank": 14,
        "brand": "어노브",
        "name": "[4년 연속 1위] 어노브 딥 데미지 헤어 트리트먼트 EX 320ml 더블/듀오 기획",
        "price": "28,800",
        "updated_at": "2026-04-24 16:00:41"
    },
    {
        "rank": 15,
        "brand": "필리밀리",
        "name": "필리밀리X챠미키티 에디션 18종 택1",
        "price": "4,560",
        "updated_at": "2026-04-24 16:00:41"
    },
    {
        "rank": 16,
        "brand": "비브리브",
        "name": "비브리브 꼬박꼬밥 고단저당 40g 6종 택1",
        "price": "3,900",
        "updated_at": "2026-04-24 16:00:41"
    },
    {
        "rank": 17,
        "brand": "투쿨포스쿨",
        "name": "[4월 올영픽/스테이셔너리 컬렉션] 투쿨포스쿨 스머징 트임 라이너 (단품/파우치증정 더블기획)",
        "price": "8,900",
        "updated_at": "2026-04-24 16:00:41"
    },
    {
        "rank": 18,
        "brand": "네이밍",
        "name": "[지성맞춤/지속력쿠션] 네이밍 올데이 마스터 쿠션 기획 (본품+리필)",
        "price": "26,900",
        "updated_at": "2026-04-24 16:00:41"
    },
    {
        "rank": 19,
        "brand": "웰라쥬",
        "name": "[속건조필수템] 웰라쥬 리얼 히알루로닉 블루 100 앰플 75ml 2입 기획",
        "price": "30,500",
        "updated_at": "2026-04-24 16:00:41"
    },
    {
        "rank": 20,
        "brand": "아누아",
        "name": "[단독기획] 아누아 피디알엔 히알루론산 캡슐 100 세럼 30mL 기획 (+30mL 리필팩)",
        "price": "26,900",
        "updated_at": "2026-04-24 16:00:41"
    }
]